{
  "resourceType": "StructureDefinition",
  "id": "2456fcec-37e3-4592-a3a7-38e2fbfa9e1e",
  "meta": {
    "versionId": "3",
    "lastUpdated": "2017-02-13T14:09:15.282+00:00"
  },
  "url": "StructureDefinition/ODA_Practitioner",
  "name": "ODA_Practitioner",
  "status": "draft",
  "date": "2017-02-09T15:25:28.633299+02:00",
  "description": "Ammattilaisen tiedot aikaan liittyen\r\n\r\nBase StructureDefinition for Practitioner Resource",
  "kind": "resource",
  "constrainedType": "Practitioner",
  "abstract": false,
  "base": "http://hl7.org/fhir/StructureDefinition/Practitioner",
  "differential": {
    "element": [
      {
        "path": "Practitioner"
      },
      {
        "path": "Practitioner.identifier",
        "min": 1,
        "max": "1"
      },
      {
        "path": "Practitioner.identifier.use",
        "max": "0"
      },
      {
        "path": "Practitioner.identifier.type",
        "max": "0"
      },
      {
        "path": "Practitioner.identifier.system",
        "definition": "Establishes the namespace in which set of possible id values is unique.\r\n\r\nTerhikki: rekisteröintinumero",
        "comments": "\r\nsee http://en.wikipedia.org/wiki/Uniform_resource_identifier"
      },
      {
        "path": "Practitioner.identifier.value",
        "definition": "The portion of the identifier typically displayed to the user and which is unique within the context of the system.\r\n\r\nTerhikki rekisteröintinumero",
        "requirements": "terhikkitunnus"
      },
      {
        "path": "Practitioner.identifier.period",
        "max": "0"
      },
      {
        "path": "Practitioner.identifier.assigner",
        "max": "0"
      },
      {
        "path": "Practitioner.active",
        "max": "0"
      },
      {
        "path": "Practitioner.name",
        "comments": "Ammilaisen nimi\r\n\r\nNames may be changed, or repudiated, or people may have different names in different contexts. Names may be divided into parts of different type that have variable significance depending on context, though the division into parts does not always matter. With personal names, the different parts may or may not be imbued with some implicit meaning; various cultures associate different importance with the name parts and the degree to which systems must care about name parts around the world varies widely.",
        "requirements": "Contact persons need to be identified by name, but it is uncommon to need details about multiple other names for that person. \r\n"
      },
      {
        "path": "Practitioner.name.use",
        "max": "0"
      },
      {
        "path": "Practitioner.name.period",
        "max": "0"
      },
      {
        "path": "Practitioner.telecom",
        "comments": "Puhelinnumero tai sähköposti\r\n\r\nPerson may have multiple ways to be contacted with different uses or applicable periods.  May need to have options for contacting the person urgently, and also to help with identification."
      },
      {
        "path": "Practitioner.telecom.value",
        "comments": "Additional text data such as phone extension numbers, or notes about use of the contact are sometimes included in the value.\r\n\r\nEsimerkiksi puhelinnumero"
      },
      {
        "path": "Practitioner.telecom.use",
        "max": "0"
      },
      {
        "path": "Practitioner.telecom.rank",
        "max": "0"
      },
      {
        "path": "Practitioner.telecom.period",
        "max": "0"
      },
      {
        "path": "Practitioner.address",
        "comments": "Note: address is for postal addresses, not physical locations.\r\n\r\nEsimerkiksi millä terveysasemalla tarjottu aika, osoite"
      },
      {
        "path": "Practitioner.address.use",
        "max": "0"
      },
      {
        "path": "Practitioner.address.type",
        "max": "0"
      },
      {
        "path": "Practitioner.address.district",
        "max": "0"
      },
      {
        "path": "Practitioner.address.state",
        "max": "0"
      },
      {
        "path": "Practitioner.address.country",
        "max": "0"
      },
      {
        "path": "Practitioner.address.period",
        "max": "0"
      },
      {
        "path": "Practitioner.birthDate",
        "max": "0"
      },
      {
        "path": "Practitioner.photo",
        "max": "0"
      },
      {
        "path": "Practitioner.practitionerRole.managingOrganization.display",
        "requirements": "Esimerkiksi terveysaseman nimi tänne"
      },
      {
        "path": "Practitioner.practitionerRole.role",
        "max": "0"
      },
      {
        "path": "Practitioner.practitionerRole.specialty",
        "requirements": "Tuleeko tänne palveluluokitus?",
        "max": "0"
      },
      {
        "path": "Practitioner.practitionerRole.period",
        "max": "0"
      },
      {
        "path": "Practitioner.practitionerRole.location",
        "comments": "Sijainti, kaupunki / alue"
      },
      {
        "path": "Practitioner.practitionerRole.location.reference",
        "requirements": "Viittaus linkkiin, missä esimerkiksi ohjeistus saapua paikanpäälle"
      },
      {
        "path": "Practitioner.practitionerRole.location.display",
        "requirements": "Sijainti, kaupunki / alue"
      },
      {
        "path": "Practitioner.practitionerRole.healthcareService",
        "comments": "Palvelun tiedot tähän resurssiin",
        "type": [
          {
            "code": "Reference",
            "profile": [
              "https://simplifier.net/ODAajanvaraus/ODAHealthcareService"
            ]
          }
        ]
      },
      {
        "path": "Practitioner.qualification",
        "max": "0"
      },
      {
        "path": "Practitioner.communication",
        "comments": "Ammattilaisen kielet\r\n\r\nThe structure aa-BB with this exact casing is one the most widely used notations for locale. However not all systems actually code this but instead have it as free text. Hence CodeableConcept instead of code as the data type."
      },
      {
        "path": "Practitioner.communication.coding.system",
        "requirements": "Need to be unambiguous about the source of the definition of the symbol.\r\n\r\nViittaus SFS kielikoodistoon tai oma value set?"
      },
      {
        "path": "Practitioner.communication.coding.userSelected",
        "max": "0"
      }
    ]
  }
}